llmlink/__init__.py
llmlink/app/App.py
llmlink/app/__init__.py
llmlink/app/utils.py
llmlink/model/Agent.py
llmlink/model/BaseModel.py
llmlink/model/Model.py
llmlink/model/__init__.py
llmlink-0.0.5.dist-info/METADATA
llmlink-0.0.5.dist-info/WHEEL
llmlink-0.0.5.dist-info/top_level.txt
llmlink-0.0.5.dist-info/RECORD
