Metadata-Version: 2.1
Name: llmlink
Version: 0.0.5
Summary: LLMLink is a Python package that allows users to easily create LLM-powered Gradio applications
Home-page: https://github.com/jacobrenn/llmlink.git
Author: Jacob Renn
Author-email: jacob.renn@squared.ai
License: Apache 2.0
Requires-Dist: transformers
Requires-Dist: langchain
Requires-Dist: openai
Requires-Dist: gradio
Requires-Dist: torch
